mcp_teams_server/__init__.py
mcp_teams_server/__main__.py
mcp_teams_server/config.py
mcp_teams_server/teams.py
iflow_mcp_mcp_teams_server-1.0.6.dist-info/METADATA
iflow_mcp_mcp_teams_server-1.0.6.dist-info/WHEEL
iflow_mcp_mcp_teams_server-1.0.6.dist-info/entry_points.txt
iflow_mcp_mcp_teams_server-1.0.6.dist-info/licenses/LICENSE.txt
iflow_mcp_mcp_teams_server-1.0.6.dist-info/licenses/NOTICE
iflow_mcp_mcp_teams_server-1.0.6.dist-info/RECORD
